DecisionProgramming/Diagram.py
DecisionProgramming/JuMP.py
DecisionProgramming/Nodes.py
DecisionProgramming/__init__.py
DecisionProgramming/juliaUtils.py
DecisionProgramming-1.0.data/scripts/pdp_setup_julia.jl
DecisionProgramming-1.0.dist-info/LICENSE
DecisionProgramming-1.0.dist-info/METADATA
DecisionProgramming-1.0.dist-info/WHEEL
DecisionProgramming-1.0.dist-info/top_level.txt
DecisionProgramming-1.0.dist-info/RECORD
