Metadata-Version: 2.1
Name: DecisionProgramming
Version: 1.0
Summary: Python interface for DecisionProgramming.jl
Home-page: https://github.com/gamma-opt/pyDecisionProgramming
Author: Jarno Rantaharju
Author-email: jarno.rantaharju@aalto.fi
License: MIT
Project-URL: Bug Tracker, https://github.com/gamma-opt/pyDecisionProgramming/issues
Project-URL: Documentation, https://gamma-opt.github.io/pyDecisionProgramming
Platform: UNKNOWN
Classifier: Programming Language :: Python :: 3
Classifier: License :: OSI Approved :: MIT License
Classifier: Operating System :: OS Independent
License-File: LICENSE
Requires-Dist: julia
Requires-Dist: numpy
